naver_config/__init__.py
naver_config/config/__init__.py
naver_config/config/core.py
naver_config/consul/__init__.py
naver_config/consul/client.py
test/__init__.py
test/config-consul-connect.py
test/config-main-test.py
test/consul-main-test.py
naver_config-0.0.2.dist-info/METADATA
naver_config-0.0.2.dist-info/WHEEL
naver_config-0.0.2.dist-info/top_level.txt
naver_config-0.0.2.dist-info/RECORD
